LICENSE.txt
MANIFEST.in
README.md
requirements.txt
setup.py
aws_glue_job_history/__init__.py
aws_glue_job_history/main.py
aws_glue_job_history.egg-info/PKG-INFO
aws_glue_job_history.egg-info/SOURCES.txt
aws_glue_job_history.egg-info/dependency_links.txt
aws_glue_job_history.egg-info/entry_points.txt
aws_glue_job_history.egg-info/requires.txt
aws_glue_job_history.egg-info/top_level.txt