Metadata-Version: 2.1
Name: aws-glue-job-history
Version: 0.0.1
Summary: aws-glue-job-history
Author: suzuki-navi
License-File: LICENSE.txt
